{
    "web":{
        "client_id":"192359318533-jvreqg87t7fgpuu6e537evv9dlfv04aa.apps.googleusercontent.com",
        "project_id":"levelpack01-379418",
        "auth_uri":"https://accounts.google.com/o/oauth2/auth",
        "token_uri":"https://oauth2.googleapis.com/token",
        "auth_provider_x509_cert_url":"https://www.googleapis.com/oauth2/v1/certs",
        "client_secret":"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",
        "redirect_uris":["http://localhost:8090"],
        "javascript_origins":["http://localhost:8090"]
        }
}